eempy/__init__.py
eempy/eem_processing/__init__.py
eempy/eem_processing/eem_processing.py
eempy/plot/__init__.py
eempy/plot/plot.py
eempy/read_data/__init__.py
eempy/read_data/read_data.py
eempy/utils/__init__.py
eempy/utils/utils.py
eem_python-1.22.dist-info/LICENSE
eem_python-1.22.dist-info/METADATA
eem_python-1.22.dist-info/WHEEL
eem_python-1.22.dist-info/top_level.txt
eem_python-1.22.dist-info/RECORD
